bin/__init__.py
bin/house.py
data/__init__.py
docs/__init__.py
modules/__init__.py
modules/modules.py
modules/test.py
modules/test_model_evaluation.py
houseprices2023xx-0.11.0.dist-info/LICENSE.md
houseprices2023xx-0.11.0.dist-info/METADATA
houseprices2023xx-0.11.0.dist-info/WHEEL
houseprices2023xx-0.11.0.dist-info/top_level.txt
houseprices2023xx-0.11.0.dist-info/RECORD
